{
  "_generated": "DO NOT EDIT - Generated from mentions-input.json via 'pnpm enrich-mentions'",
  "mentions": [
    {
      "id": "645b5836",
      "type": "article",
      "url": "https://codeburst.io/the-front-end-checklist-app-a1faa882cad6",
      "date": "2026-05-29",
      "featured": false,
      "title": "",
      "source": "codeburst.io"
    },
    {
      "id": "da6e6d73",
      "type": "article",
      "url": "https://www.sitepoint.com/web-development-checklists/",
      "date": "2026-05-29",
      "featured": false,
      "title": "",
      "source": "sitepoint.com"
    },
    {
      "id": "80a12b14",
      "type": "tweet",
      "url": "https://x.com/madzadev/status/1873297404390408372?s=20",
      "date": "2024-12-29",
      "featured": true,
      "tweetId": "1873297404390408372",
      "author": "Madza 👨‍💻⚡",
      "authorUrl": "https://x.com/madzadev",
      "avatarUrl": "https://pbs.twimg.com/profile_images/1526471322762715136/w25QtNnl_normal.jpg",
      "handle": "madzadev",
      "content": "Here are some good tips not only for performance but also for good practices in general: https://t.co/2FHleW7sHE",
      "likes": 1
    },
    {
      "id": "820785d6",
      "type": "tweet",
      "url": "https://x.com/guillaume_rygn/status/1862044944036135221?s=20",
      "date": "2024-11-28",
      "featured": true,
      "tweetId": "1862044944036135221",
      "author": "code w/Guillaume 💻",
      "authorUrl": "https://x.com/guillaume_rygn",
      "avatarUrl": "https://pbs.twimg.com/profile_images/1483519295288233991/9igtPNRr_normal.jpg",
      "handle": "guillaume_rygn",
      "content": "J'ai trouvé un site qui recense toutes les bonnes pratiques à avoir sur son site sous forme de Checklist✅\n\nÇa s'appelle https://t.co/wGx6qHxyDd ! c'est pratique pour ne rien oublier (performances, SEO, images etc)\nJe fais toujours un check de cette liste avant de lancer un… pic.twitter.com/hL35ziltTL",
      "mediaUrl": "https://pbs.twimg.com/media/GddP_cdXYAA0DK9.jpg",
      "likes": 223
    },
    {
      "id": "0cd85b83",
      "type": "tweet",
      "url": "https://x.com/Manz/status/1678348970438041600?s=20",
      "date": "2023-07-10",
      "featured": true,
      "tweetId": "1678348970438041600",
      "author": "Manz 🇮🇨⚡👾",
      "authorUrl": "https://x.com/Manz",
      "avatarUrl": "https://pbs.twimg.com/profile_images/1386378668717613060/Ghr2DQuO_normal.jpg",
      "handle": "Manz",
      "content": "⚡Mis otras redes: https://t.co/YGtxSUGe4S\n➡ Frontend Checklist: https://t.co/T4L9iAKZkv\n🎬 Buenas prácticas (1): https://t.co/IzhOvwoOJQ",
      "likes": 2
    },
    {
      "id": "df52a663",
      "type": "tweet",
      "url": "https://x.com/guillaume_rygn/status/1630132469264424960?s=20",
      "date": "2023-02-27",
      "featured": false,
      "tweetId": "1630132469264424960",
      "author": "code w/Guillaume 💻",
      "authorUrl": "https://x.com/guillaume_rygn",
      "avatarUrl": "https://pbs.twimg.com/profile_images/1483519295288233991/9igtPNRr_normal.jpg",
      "handle": "guillaume_rygn",
      "content": "J'ai trouvé un site qui recense toutes les bonnes pratiques à avoir sur son site sous forme de Checklist✅\n\nÇa s'appelle https://t.co/wGx6qHxyDd! c'est pratique pour ne rien oublier (performances, SEO, images etc)\nJe fais toujours un check de cette liste avant de lancer un site👀 pic.twitter.com/RUmLjGz9Qe",
      "mediaUrl": "https://pbs.twimg.com/media/Fp9k16PXsAQx_PD.jpg",
      "likes": 468
    },
    {
      "id": "5b17b97a",
      "type": "tweet",
      "url": "https://x.com/donwolfonline/status/1626912814391607298?s=20",
      "date": "2023-02-18",
      "featured": false,
      "tweetId": "1626912814391607298",
      "author": "Frederick Dineen",
      "authorUrl": "https://x.com/donwolfonline",
      "avatarUrl": "https://pbs.twimg.com/profile_images/1966594105674174464/Ejnic0CW_normal.jpg",
      "handle": "donwolfonline",
      "content": "📌 A very awesome website for Front-End developers 👌😍\nIt gives you a list of the things you need to adjust when making a new design with HTML / CSS / JAVASCRIPT and even SEO ✅\nTasks are divided according to importancehttps://t.co/JzjzWZIk5d",
      "likes": 0
    },
    {
      "id": "a2cc909d",
      "type": "tweet",
      "url": "https://x.com/mrdavediamond/status/1549207668652638210?s=20",
      "date": "2022-07-19",
      "featured": false,
      "tweetId": "1549207668652638210",
      "author": "Dave Diamond",
      "authorUrl": "https://x.com/mrdavediamond",
      "avatarUrl": "https://pbs.twimg.com/profile_images/1628243766841868288/V5gFatf4_normal.jpg",
      "handle": "mrdavediamond",
      "content": "Killer 📑 #checklist from @TheDavidDias!\n\nSuper helpful if you're web designer, #startup founder, and compulsory if you're a #FrontEndDeveloper.\n\nCheck this  >> https://t.co/5pOsUuL8wk  👀\n\n #SeoTools #Web3 #design",
      "likes": 1
    },
    {
      "id": "4f5d3320",
      "type": "tweet",
      "url": "https://x.com/Sumukhmg/status/1526434885283418112?s=20",
      "date": "2022-05-17",
      "featured": false,
      "tweetId": "1526434885283418112",
      "author": "Sumukh",
      "authorUrl": "https://x.com/Sumukhmg",
      "avatarUrl": "https://pbs.twimg.com/profile_images/1832443952600887296/HEDtuy9C_normal.jpg",
      "handle": "Sumukhmg",
      "content": "⑤ Frontend checklist: The Front-End Checklist is an exhaustive list of all elements you need to have / to test before launching your website / HTML page to production.\n🔗 https://t.co/DmmGMvrWyF pic.twitter.com/vv5yMt5htG",
      "mediaUrl": "https://pbs.twimg.com/media/FS78b7MUsAAinfw.jpg",
      "likes": 3
    },
    {
      "id": "4e1d634e",
      "type": "tweet",
      "url": "https://x.com/ishrratumar/status/1520752430245240832?s=20",
      "date": "2022-05-01",
      "featured": false,
      "tweetId": "1520752430245240832",
      "author": "Ishrat",
      "authorUrl": "https://x.com/ishrratumar",
      "avatarUrl": "https://pbs.twimg.com/profile_images/1503799335292743687/zUfzmZA8_normal.jpg",
      "handle": "ishrratumar",
      "content": "3. Front-End Checklist\n\n✍️ The Front-End Checklist is a detailed list of all you need to test before publishing your site.https://t.co/iJIESy92b3 pic.twitter.com/nK6vxDVKUI",
      "mediaUrl": "https://pbs.twimg.com/media/FRrMRgKUYAAgT3l.jpg",
      "likes": 10
    },
    {
      "id": "df75080f",
      "type": "tweet",
      "url": "https://x.com/code_rams/status/1515253474165932034?s=20",
      "date": "2022-04-16",
      "featured": false,
      "tweetId": "1515253474165932034",
      "author": "Ramya Chinnadurai 🚀",
      "authorUrl": "https://x.com/code_rams",
      "avatarUrl": "https://pbs.twimg.com/profile_images/1491644590583345152/0_qYmn9E_normal.jpg",
      "handle": "code_rams",
      "content": "8. The front-end checklist\n\nThe Complete checklist for particularly perfect for modern websites and meticulous developers!https://t.co/gmQ7GkcxzN pic.twitter.com/BW6FWaWjLT",
      "mediaUrl": "https://pbs.twimg.com/ext_tw_video_thumb/1515251863729459203/pu/img/1hyWWe0HVAgzae3W.jpg",
      "likes": 49
    },
    {
      "id": "65b7feb8",
      "type": "tweet",
      "url": "https://x.com/devatTheCave/status/1441398475824893952?s=20",
      "date": "2021-09-24",
      "featured": false,
      "tweetId": "1441398475824893952",
      "author": "Mahmood Tareq",
      "authorUrl": "https://x.com/devatTheCave",
      "avatarUrl": "https://pbs.twimg.com/profile_images/1784715641515130880/d7-QYWLz_normal.jpg",
      "handle": "devatTheCave",
      "content": "3- The front-end checklist\n\nThis is the website was the reason I made this list\n\nIt allows you to learn and follow the rules when it comes to front-end web development\n\nIt tells you the best practices you should use for building a websitehttps://t.co/pfB2W8QbY3 pic.twitter.com/ohClvvoYDE",
      "mediaUrl": "https://pbs.twimg.com/media/FADgFTMX0AA-3q7.jpg",
      "likes": 63
    },
    {
      "id": "4ea365bb",
      "type": "tweet",
      "url": "https://x.com/grandemayta/status/1196432555408576513?s=20",
      "date": "2019-11-18",
      "featured": false,
      "tweetId": "1196432555408576513",
      "author": "Gabriel Mayta",
      "authorUrl": "https://x.com/grandemayta",
      "avatarUrl": "https://pbs.twimg.com/profile_images/1422842448267653122/RyKFEelV_normal.jpg",
      "handle": "grandemayta",
      "content": "Are you new in the Frontend world?\nHere you can find three useful links about:\n\n🗂Guidelines -> https://t.co/v1pku1sOhL\n💎Design -> https://t.co/IEnEDmqE8p\n🎮Performance -> https://t.co/WeJq77EdYY\nBonus:\n👍Live Checklist -> https://t.co/P2kjUo1L0G#frontend #webdevelopment",
      "likes": 1
    },
    {
      "id": "ee3f6e51",
      "type": "tweet",
      "url": "https://x.com/_DZGND/status/1186687665351073792?s=20",
      "date": "2019-10-22",
      "featured": false,
      "tweetId": "1186687665351073792",
      "author": "Dareth NHANG",
      "authorUrl": "https://x.com/_DZGND",
      "avatarUrl": "https://pbs.twimg.com/profile_images/1879907154808778752/P-36bbNT_normal.jpg",
      "handle": "_DZGND",
      "content": "Pour nous, les #dev (#front)… Mais aussi pour #LesClients ou les personnes qui pensent que développer un site internet, c'est juste quelques clics… https://t.co/WTElZfEotP\n\nEt je ne vous parle pas du #back, de la #sécurité, de la gestion des serveurs, etc. !!! pic.twitter.com/LqpWtpNjoa",
      "mediaUrl": "https://pbs.twimg.com/media/EHf2JIiXUAETqMS.jpg",
      "likes": 2
    },
    {
      "id": "b5105424",
      "type": "tweet",
      "url": "https://x.com/hdjirdeh/status/1162450424244236288?s=20",
      "date": "2019-08-16",
      "featured": true,
      "tweetId": "1162450424244236288",
      "author": "Houssein Djirdeh",
      "authorUrl": "https://x.com/hdjirdeh",
      "avatarUrl": "https://pbs.twimg.com/profile_images/1460651862340915201/w8Zva6LO_normal.jpg",
      "handle": "hdjirdeh",
      "content": "David is super passionate about everything he works on and was solely responsible for building https://t.co/8UEvCMDb3A\n\nFor any Toronto folks who follow me looking to hire, reach out to him! https://t.co/TRaDm0FTYl",
      "likes": 9
    },
    {
      "id": "14eaba8b",
      "type": "tweet",
      "url": "https://x.com/codepo8/status/1046844559781715968?s=20",
      "date": "2018-10-01",
      "featured": false,
      "tweetId": "1046844559781715968",
      "author": "Chris Heilmann codepo8.bsky.social",
      "authorUrl": "https://x.com/codepo8",
      "avatarUrl": "https://pbs.twimg.com/profile_images/1969442465976336384/jeDfC3x9_normal.jpg",
      "handle": "codepo8",
      "content": "Fun to meet @thedaviddias of frontend checklist fame. #WEBU18 https://t.co/Ggh5mSsFgM give him thanks when you meet him. Curating something like this looks easy but is a hell of a job",
      "likes": 25
    },
    {
      "id": "52898468",
      "type": "tweet",
      "url": "https://x.com/TheDavidDias/status/1030437747104854017?s=20",
      "date": "2018-08-17",
      "featured": false,
      "tweetId": "1030437747104854017",
      "author": "David Dias",
      "authorUrl": "https://x.com/TheDavidDias",
      "avatarUrl": "https://pbs.twimg.com/profile_images/1948133704238260225/xRTA829j_normal.jpg",
      "handle": "TheDavidDias",
      "content": "Thanks @ResWebDes for mentioning the Front-End Performance Checklist in your last newsletter #322! #FrontEndChecklist #FrontEndFriday #FrontEnd #Checklist #thank you pic.twitter.com/gbVrx6B1Fk",
      "mediaUrl": "https://pbs.twimg.com/media/DkzZev7UYAUgvNF.jpg",
      "likes": 3
    },
    {
      "id": "06e9283f",
      "type": "tweet",
      "url": "https://x.com/TheDavidDias/status/1022166928444612608?s=20",
      "date": "2018-07-25",
      "featured": false,
      "tweetId": "1022166928444612608",
      "author": "David Dias",
      "authorUrl": "https://x.com/TheDavidDias",
      "avatarUrl": "https://pbs.twimg.com/profile_images/1948133704238260225/xRTA829j_normal.jpg",
      "handle": "TheDavidDias",
      "content": "The Front-End Performance Checklist is listed on JavaScript Weekly Newsletter! 😱 😍 😇 https://t.co/eJspXW1iMC #javascript #FrontEndChecklist #newsletter #trending pic.twitter.com/qYmcp51KyH",
      "mediaUrl": "https://pbs.twimg.com/media/Di93ZtYWwAE5MPj.jpg",
      "likes": 3
    },
    {
      "id": "5ab4e4b1",
      "type": "article",
      "url": "https://levelup.gitconnected.com/3-essential-front-end-checklists-for-web-developers-d873b226b1f0",
      "date": "2018-07-24",
      "featured": true,
      "title": "3 Essential Front-End Checklists for Web Developers",
      "source": "Medium",
      "author": "David Dias",
      "excerpt": "Ensure your web applications are air tight and high quality with these open source checklists covering engineering, design, and performance",
      "ogImage": "https://miro.medium.com/v2/resize:fit:1200/1*wAs_2vEPznyXz49izdZNwg.jpeg",
      "favicon": "https://levelup.gitconnected.com/favicon.ico"
    },
    {
      "id": "ef2849b4",
      "type": "tweet",
      "url": "https://x.com/codepo8/status/997740512806408192?s=20",
      "date": "2018-05-19",
      "featured": true,
      "tweetId": "997740512806408192",
      "author": "Chris Heilmann codepo8.bsky.social",
      "authorUrl": "https://x.com/codepo8",
      "avatarUrl": "https://pbs.twimg.com/profile_images/1969442465976336384/jeDfC3x9_normal.jpg",
      "handle": "codepo8",
      "content": "Check the 🔥 Front-End Checklist Application 🔥 for modern websites and meticulous developers! With more than 20 000 🌟 on #Github, now you can use it on your daily workflow and generate reports 📑! https://t.co/IV6fcMePix #FrontEndChecklist #FrontEnd #Tool #Web via @thedaviddias",
      "mediaUrl": "https://pbs.twimg.com/card_img/2060282638141632517/vwydf3bQ?format=jpg&name=800x419",
      "likes": 403
    },
    {
      "id": "a19e9d4c",
      "type": "tweet",
      "url": "https://x.com/Astro_Deja/status/981549240626417665?s=20",
      "date": "2018-04-04",
      "featured": false,
      "tweetId": "981549240626417665",
      "author": ";",
      "authorUrl": "https://x.com/Astro_Deja",
      "avatarUrl": "https://pbs.twimg.com/profile_images/1210275549568028682/TGXaoqd-_normal.jpg",
      "handle": "Astro_Deja",
      "content": "#100DaysOfCode #CodeNewbie\n\nLook what I found on @github 🙌🏿😵🙌🏿 Will be using the #FrontEndChecklist from now on!!! The only checklist you will ever need as a #FrontEnd #WebDev\n\nThanks, @thedaviddias !!!https://t.co/TlzbcM8syG",
      "likes": 17
    },
    {
      "id": "78602c2c",
      "type": "tweet",
      "url": "https://x.com/1stwebdesigner/status/979085960146227201?s=20",
      "date": "2018-03-28",
      "featured": false,
      "tweetId": "979085960146227201",
      "author": "1stWebDesigner",
      "authorUrl": "https://x.com/1stwebdesigner",
      "avatarUrl": "https://pbs.twimg.com/profile_images/1220368801113440256/z9ZkPaGb_normal.jpg",
      "handle": "1stwebdesigner",
      "content": "The Front-End Checklist https://t.co/J8mEgg4zwe pic.twitter.com/5Pj5YLbx8i",
      "mediaUrl": "https://pbs.twimg.com/media/DZZpfcSUMAEcjyZ.jpg",
      "likes": 38
    },
    {
      "id": "8e08643c",
      "type": "tweet",
      "url": "https://x.com/forwebdev/status/976777682548649986?s=20",
      "date": "2018-03-22",
      "featured": false,
      "tweetId": "976777682548649986",
      "author": "For Web 🇺🇦",
      "authorUrl": "https://x.com/forwebdev",
      "avatarUrl": "https://pbs.twimg.com/profile_images/1643693635475521536/tp_nbsHs_normal.jpg",
      "handle": "forwebdev",
      "content": "The Front-End Checklist\n\nОбъёмный чеклист и рекомендации для проверки всех аспектов фронтенда сайта, от разметки и доступности до производительности.\n\nТеперь и в виде удобного сайта с возможностью печати → https://t.co/vKaYAr2AJP pic.twitter.com/8CYUztjemR",
      "mediaUrl": "https://pbs.twimg.com/media/DY42H7EWsAA7kMf.jpg",
      "likes": 50
    },
    {
      "id": "c952930a",
      "type": "tweet",
      "url": "https://x.com/speckyboy/status/975824505204609025?s=20",
      "date": "2018-03-19",
      "featured": true,
      "tweetId": "975824505204609025",
      "author": "Speckyboy",
      "authorUrl": "https://x.com/speckyboy",
      "avatarUrl": "https://pbs.twimg.com/profile_images/1833187020996333568/WrW1WadX_normal.png",
      "handle": "speckyboy",
      "content": "The Front-End Checklist https://t.co/EKgCry8eLk pic.twitter.com/dfnUDrclwI",
      "mediaUrl": "https://pbs.twimg.com/media/DYrTNyWXUAE6U9f.jpg",
      "likes": 92
    },
    {
      "id": "569ad69f",
      "type": "tweet",
      "url": "https://x.com/SoyJuanMacias/status/974736513266339840?s=20",
      "date": "2018-03-16",
      "featured": false,
      "tweetId": "974736513266339840",
      "author": "Juan Macias",
      "authorUrl": "https://x.com/SoyJuanMacias",
      "avatarUrl": "https://pbs.twimg.com/profile_images/1612607291366297600/ugafEXtT_normal.jpg",
      "handle": "SoyJuanMacias",
      "content": "@thedaviddias Teaching us how to start an Open-Source project and his awesome tool https://t.co/g1QWcoqobr. One of the best meetup I’ve been! Thanks @thedaviddias for all and @IronhackMAD for give us your space! pic.twitter.com/Hyd4UD8aqL",
      "mediaUrl": "https://pbs.twimg.com/media/DYb1rxDWAAAf3XP.jpg",
      "likes": 1
    },
    {
      "id": "d666f531",
      "type": "tweet",
      "url": "https://x.com/qudusdev/status/949679725689167872?s=20",
      "date": "2018-01-06",
      "featured": false,
      "tweetId": "949679725689167872",
      "author": "Qudus",
      "authorUrl": "https://x.com/qudusdev",
      "avatarUrl": "https://pbs.twimg.com/profile_images/793780072561934336/IuuT2K9U_normal.jpg",
      "handle": "qudusdev",
      "content": "Wowhttps://t.co/qROdcFwWHa",
      "likes": 0
    },
    {
      "id": "24980364",
      "type": "article",
      "url": "https://css-tricks.com/front-end-performance-checklist/",
      "date": "2018-01-04",
      "featured": true,
      "title": "Front-End Performance Checklist | CSS-Tricks",
      "source": "CSS-Tricks",
      "excerpt": "Vitaly Friedman swings wide with a massive list of performance considerations. It&#039;s a well-considered mix of old tactics (cutting the mustard, progressive",
      "ogImage": "https://i0.wp.com/css-tricks.com/wp-content/uploads/2021/12/default-social-css-tricks.png",
      "favicon": "https://css-tricks.com/favicon.ico"
    },
    {
      "id": "6209f678",
      "type": "tweet",
      "url": "https://x.com/TheDavidDias/status/943023612549726208?s=20",
      "date": "2017-12-19",
      "featured": false,
      "tweetId": "943023612549726208",
      "author": "David Dias",
      "authorUrl": "https://x.com/TheDavidDias",
      "avatarUrl": "https://pbs.twimg.com/profile_images/1948133704238260225/xRTA829j_normal.jpg",
      "handle": "TheDavidDias",
      "content": "Hey @twilio, thanks for sharing the #FrontEndChecklist in your last Twilio developer digest! As you can see, I always read your newsletter 😅😂 #opensource #frontend #twilio pic.twitter.com/3T0dTdGNaV",
      "mediaUrl": "https://pbs.twimg.com/media/DRZK9-hXUAATykw.jpg",
      "likes": 10
    },
    {
      "id": "15054d52",
      "type": "article",
      "url": "https://www.noupe.com/magazine/design/perfect-for-web-developers-the-front-end-checklist-ensures-code-quality.html",
      "date": "2017-12-13",
      "featured": true,
      "title": "Perfect for Web Developers: The Front-End Checklist Ensures Code Quality | NOUPE",
      "source": "noupe",
      "author": "Noupe Editorial Team",
      "excerpt": "Following checklists is proven to help improve the quality of what the checklist was designed for. This front-end checklist is dedicated to web development",
      "ogImage": "https://www.noupe.com/wp-content/uploads/2017/12/checklist-2589418_1280.jpg",
      "favicon": "https://www.noupe.com/favicon.ico"
    },
    {
      "id": "b33f554a",
      "type": "tweet",
      "url": "https://x.com/440UrPp/status/937815946089107456?s=20",
      "date": "2017-12-04",
      "featured": false,
      "tweetId": "937815946089107456",
      "author": "kgothatso@8333.mobi",
      "authorUrl": "https://x.com/440UrPp",
      "avatarUrl": "https://pbs.twimg.com/profile_images/1978138753722937344/bU8MtkM2_normal.jpg",
      "handle": "440UrPp",
      "content": "I went through my first front end check list test on https://t.co/rm5BvM3eAB and I have to say my web dev sucks! So many points were lost to very straight forward things. I got an E for the site I'm currently on.\n\nNow imma need to go update all the websites I've ever worked on. pic.twitter.com/J5u4pBLEyI",
      "mediaUrl": "https://pbs.twimg.com/tweet_video_thumb/DQPKeWKXcAEoDuN.jpg",
      "likes": 0
    },
    {
      "id": "07d534f1",
      "type": "article",
      "url": "https://css-tricks.com/front-end-checklist-just-tool-everything-depends/",
      "date": "2017-11-30",
      "featured": true,
      "title": "The Front-End Checklist is just a tool... everything depends on you. | CSS-Tricks",
      "source": "CSS-Tricks",
      "excerpt": "One month ago, I launched the Front-End Checklist on GitHub. In less than 2 weeks, more than 10,000 people around the world starred the repository. That was",
      "ogImage": "https://i0.wp.com/css-tricks.com/wp-content/uploads/2017/11/image2.jpg",
      "favicon": "https://css-tricks.com/favicon.ico"
    },
    {
      "id": "80c929ce",
      "type": "tweet",
      "url": "https://x.com/disco_lu/status/934247068146679808?s=20",
      "date": "2017-11-25",
      "featured": false,
      "tweetId": "934247068146679808",
      "author": "luis.",
      "authorUrl": "https://x.com/disco_lu",
      "avatarUrl": "https://pbs.twimg.com/profile_images/2046287739038138368/VDIwR0e2_normal.jpg",
      "handle": "disco_lu",
      "content": "This frontend checklist from @thedaviddias looks special. https://t.co/WsQVmlZK1M pic.twitter.com/BRKsbM8DrO",
      "mediaUrl": "https://pbs.twimg.com/media/DPccwSuUQAA1OAu.jpg",
      "likes": 1
    },
    {
      "id": "0cca0ae1",
      "type": "tweet",
      "url": "https://x.com/TheDavidDias/status/932653865140232192?s=20",
      "date": "2017-11-20",
      "featured": false,
      "tweetId": "932653865140232192",
      "author": "David Dias",
      "authorUrl": "https://x.com/TheDavidDias",
      "avatarUrl": "https://pbs.twimg.com/profile_images/1948133704238260225/xRTA829j_normal.jpg",
      "handle": "TheDavidDias",
      "content": "A 🙌 HUGE thanks to @KeyCDN who sponsored the #FrontEndChecklist! #thankyou #youarethebest #cdn pic.twitter.com/Qi2QmwYAP3",
      "mediaUrl": "https://pbs.twimg.com/tweet_video_thumb/DPFzkesXcAEWK1C.jpg",
      "likes": 4
    },
    {
      "id": "8a95d3ff",
      "type": "tweet",
      "url": "https://x.com/KrasimirTsonev/status/925581418541002752?s=20",
      "date": "2017-11-01",
      "featured": true,
      "tweetId": "925581418541002752",
      "author": "Krasimir",
      "authorUrl": "https://x.com/KrasimirTsonev",
      "avatarUrl": "https://pbs.twimg.com/profile_images/1324953787275091974/EW2-Fv9f_normal.jpg",
      "handle": "KrasimirTsonev",
      "content": "If you are a front-end developer make sure that you check this page https://t.co/oDJF7PYrsA Front-End Checklist #fe #javascript",
      "likes": 15
    },
    {
      "id": "fdacbb8f",
      "type": "tweet",
      "url": "https://x.com/TheDavidDias/status/923918497918287873?s=20",
      "date": "2017-10-27",
      "featured": false,
      "tweetId": "923918497918287873",
      "author": "David Dias",
      "authorUrl": "https://x.com/TheDavidDias",
      "avatarUrl": "https://pbs.twimg.com/profile_images/1948133704238260225/xRTA829j_normal.jpg",
      "handle": "TheDavidDias",
      "content": "🔥The #frontendchecklist is above 10 000 stars in less 2 weeks! 😱😱😲 @github #FridayFeeling #sucess #github #frontend #cantbelieve pic.twitter.com/qqZtGGDfZL",
      "mediaUrl": "https://pbs.twimg.com/media/DNJq95pW0AAKtTK.jpg",
      "likes": 7
    },
    {
      "id": "882d0af4",
      "type": "tweet",
      "url": "https://x.com/housecor/status/923754949556785153?s=20",
      "date": "2017-10-27",
      "featured": true,
      "tweetId": "923754949556785153",
      "author": "Cory House",
      "authorUrl": "https://x.com/housecor",
      "avatarUrl": "https://pbs.twimg.com/profile_images/1963593369306750976/7gPWqEa8_normal.jpg",
      "handle": "housecor",
      "content": "Hey David, that list is epic! I have a tweet scheduled for tomorrow on it. Thanks for the feedback, and thank for sharing the list!",
      "likes": 1
    },
    {
      "id": "17b75250",
      "type": "tweet",
      "url": "https://x.com/TheDavidDias/status/923603765768347648?s=20",
      "date": "2017-10-26",
      "featured": false,
      "tweetId": "923603765768347648",
      "author": "David Dias",
      "authorUrl": "https://x.com/TheDavidDias",
      "avatarUrl": "https://pbs.twimg.com/profile_images/1948133704238260225/xRTA829j_normal.jpg",
      "handle": "TheDavidDias",
      "content": "The #frontendchecklist is trending on @TrendingGithub @github this week till today! Don't know how to thank the community for such support! pic.twitter.com/BNB6ai3XNE",
      "mediaUrl": "https://pbs.twimg.com/media/DNFMrcPW0AQ-99F.jpg",
      "likes": 3
    }
  ]
}
